spaceai/__init__.py
spaceai/benchmark/__init__.py
spaceai/benchmark/benchmark.py
spaceai/benchmark/callbacks/__init__.py
spaceai/benchmark/callbacks/callback.py
spaceai/benchmark/callbacks/handler.py
spaceai/benchmark/callbacks/system.py
spaceai/benchmark/esa.py
spaceai/benchmark/nasa.py
spaceai/data/__init__.py
spaceai/data/anomaly_dataset.py
spaceai/data/esa.py
spaceai/data/nasa.py
spaceai/data/utils.py
spaceai/models/__init__.py
spaceai/models/anomaly/__init__.py
spaceai/models/anomaly/detector.py
spaceai/models/anomaly/error_based_detector.py
spaceai/models/anomaly/telemanom.py
spaceai/models/predictors/__init__.py
spaceai/models/predictors/esn.py
spaceai/models/predictors/lstm.py
spaceai/models/predictors/seq_model.py
spaceai-0.2.0.dist-info/METADATA
spaceai-0.2.0.dist-info/WHEEL
spaceai-0.2.0.dist-info/RECORD
