Metadata-Version: 2.1
Name: spaceai
Version: 0.2.0
Summary: A Python library for space AI benchmarking
Home-page: https://github.com/continualist/space-ai
License: MIT
Author: ContinualIST
Author-email: valerio.decaro@di.unipi.it
Maintainer: Valerio De Caro
Maintainer-email: valerio.decaro@di.unipi.it
Requires-Python: >=3.10,<4.0
Classifier: License :: OSI Approved :: MIT License
Classifier: Programming Language :: Python :: 3
Classifier: Programming Language :: Python :: 3.10
Classifier: Programming Language :: Python :: 3.11
Classifier: Programming Language :: Python :: 3.12
Classifier: Programming Language :: Python :: 3.13
Requires-Dist: argparse (>=1.4.0,<2.0.0)
Requires-Dist: datetime (>=5.5,<6.0)
Requires-Dist: logging (>=0.4.9.6,<0.5.0.0)
Requires-Dist: more-itertools (>=10.3.0,<11.0.0)
Requires-Dist: numpy (>=2.1.3,<3.0.0)
Requires-Dist: pandas (>=2.2.2,<3.0.0)
Requires-Dist: psutil (>=6.1.0,<7.0.0)
Requires-Dist: requests (>=2.32.3,<3.0.0)
Requires-Dist: scikit-learn (>=1.5.1,<2.0.0)
Requires-Dist: torchdyno (>=0.2.3,<0.3.0)
Requires-Dist: tqdm (>=4.66.5,<5.0.0)
Project-URL: Repository, https://github.com/continualist/space-ai
